{
    "nodetree": [
        {
            "link": [
                {
                    "fromNode": "0000000000000000",
                    "fromSocket": "0000000000000000",
                    "toNode": "0200000000000000",
                    "toSocket": "0000000000000000"
                },
                {
                    "fromNode": "0100000000000000",
                    "fromSocket": "0000000000000000",
                    "toNode": "0200000000000000",
                    "toSocket": "0100000000000000"
                }
            ],
            "node": [
                {
                    "data": ":0<82;<1><550000;0<82;<1><550000;0<82;<1><550000",
                    "input": [
                        {
                            "data": "<0<82;<1><550000?0<82;<1><550000?0<82;<1><550000",
                            "input": "01",
                            "linked": "00"
                        }
                    ],
                    "output": [
                        {
                            "data": "<0<82;<1><550000?0<82;<1><550000?0<82;<1><550000",
                            "input": "00",
                            "linked": "01"
                        }
                    ]
                },
                {
                    "data": "40;12;<1><55000050;12;<1><55000050;12;<1><550000",
                    "input": [
                        {
                            "data": "<0<82;<1><550000?0<82;<1><550000?0<82;<1><550000",
                            "input": "01",
                            "linked": "00"
                        }
                    ],
                    "output": [
                        {
                            "data": "<0<82;<1><550000?0<82;<1><550000?0<82;<1><550000",
                            "input": "00",
                            "linked": "01"
                        }
                    ]
                },
                {
                    "data": "90:92;<1><550000:0:92;<1><550000:0:92;<1><550000",
                    "input": [
                        {
                            "data": "<0<82;<1><550000?0<82;<1><550000?0<82;<1><550000",
                            "input": "01",
                            "linked": "01"
                        },
                        {
                            "data": "<0<82;<1><550000?0<82;<1><550000?0<82;<1><550000",
                            "input": "01",
                            "linked": "01"
                        }
                    ],
                    "output": [
                        {
                            "data": "<0<82;<1><550000?0<82;<1><550000?0<82;<1><550000",
                            "input": "00",
                            "linked": "00"
                        }
                    ]
                }
            ]
        }
    ]
}